dj_image_uploader_widget/__init__.py
dj_image_uploader_widget/apps.py
dj_image_uploader_widget/fields.py
dj_image_uploader_widget/oss.py
dj_image_uploader_widget/views.py
dj_image_uploader_widget/widgets.py
dj_image_uploader_widget/static/uploader/css/uploader.css
dj_image_uploader_widget/static/uploader/js/uploader.js
dj_image_uploader_widget/templates/dj_image_uploader_widget/uploader.html
dj_image_uploader_widget-0.4.9.dist-info/licenses/LICENSE
dj_image_uploader_widget-0.4.9.dist-info/METADATA
dj_image_uploader_widget-0.4.9.dist-info/WHEEL
dj_image_uploader_widget-0.4.9.dist-info/top_level.txt
dj_image_uploader_widget-0.4.9.dist-info/RECORD
