Metadata-Version: 2.4
Name: dj-image-uploader-widget
Version: 0.4.9
Summary: Django OSS Image Upload Widget with Customizable Configuration
Home-page: https://github.com/ren000thomas/dj-image-uploader-widget
Author: Ren Thomas
Author-email: ren000thomas@gmail.com
License: MIT
Classifier: Framework :: Django
Classifier: Programming Language :: Python :: 3
Classifier: License :: OSI Approved :: MIT License
License-File: LICENSE
Requires-Dist: Django>=4.0
Requires-Dist: oss2>=2.15.0
Dynamic: author
Dynamic: author-email
Dynamic: classifier
Dynamic: description
Dynamic: description-content-type
Dynamic: home-page
Dynamic: license
Dynamic: license-file
Dynamic: requires-dist
Dynamic: summary
